pushover/__init__.py
pushover_api-0.0.0.dist-info/METADATA
pushover_api-0.0.0.dist-info/WHEEL
pushover_api-0.0.0.dist-info/RECORD
