Metadata-Version: 2.1
Name: pushover-api
Version: 0.0.0
Summary: 
Author: Elvir Muslic
Author-email: elvirmuslic.dev@gmail.com
Requires-Python: >=3.10,<4.0
Classifier: Programming Language :: Python :: 3
Classifier: Programming Language :: Python :: 3.10
Classifier: Programming Language :: Python :: 3.11
Requires-Dist: pre-commit (>=3.2.2,<4.0.0)
Requires-Dist: pytest (>=7.3.1,<8.0.0)
